semanticscout/__init__.py
semanticscout/__main__.py
semanticscout/config.py
semanticscout/logging_config.py
semanticscout/mcp_server.py
semanticscout/paths.py
semanticscout/ast_processing/__init__.py
semanticscout/ast_processing/ast_cache.py
semanticscout/ast_processing/ast_processor.py
semanticscout/config/__init__.py
semanticscout/config/enhancement_config.py
semanticscout/dependency_analysis/__init__.py
semanticscout/dependency_analysis/dependency_router.py
semanticscout/dependency_analysis/strategies.py
semanticscout/dependency_graph/__init__.py
semanticscout/dependency_graph/dependency_cache.py
semanticscout/dependency_graph/dependency_graph.py
semanticscout/embeddings/__init__.py
semanticscout/embeddings/base.py
semanticscout/embeddings/ollama_provider.py
semanticscout/embeddings/sentence_transformer_provider.py
semanticscout/indexer/__init__.py
semanticscout/indexer/change_detector.py
semanticscout/indexer/change_event_processor.py
semanticscout/indexer/code_chunker.py
semanticscout/indexer/delta_indexer.py
semanticscout/indexer/file_change_events.py
semanticscout/indexer/file_classifier.py
semanticscout/indexer/file_discovery.py
semanticscout/indexer/git_change_detector.py
semanticscout/indexer/pipeline.py
semanticscout/language_detection/__init__.py
semanticscout/language_detection/project_language_detector.py
semanticscout/performance/__init__.py
semanticscout/performance/memory.py
semanticscout/performance/metrics.py
semanticscout/performance/parallel.py
semanticscout/query_analysis/__init__.py
semanticscout/query_analysis/query_analyzer.py
semanticscout/retriever/__init__.py
semanticscout/retriever/context_expander.py
semanticscout/retriever/hybrid_retriever.py
semanticscout/retriever/query_processor.py
semanticscout/retriever/semantic_search.py
semanticscout/security/__init__.py
semanticscout/security/validators.py
semanticscout/symbol_table/__init__.py
semanticscout/symbol_table/symbol_table.py
semanticscout/tracking/__init__.py
semanticscout-3.4.2.dist-info/licenses/LICENSE
semanticscout-3.4.2.dist-info/METADATA
semanticscout-3.4.2.dist-info/WHEEL
semanticscout-3.4.2.dist-info/entry_points.txt
semanticscout-3.4.2.dist-info/top_level.txt
semanticscout-3.4.2.dist-info/RECORD
