Metadata-Version: 2.4
Name: semanticscout
Version: 3.4.2
Summary: A language-aware semantic code search MCP server with intelligent filtering and 9.3x better dependency analysis
Author-email: Psynosaur <psynosaur@gmail.com>
Maintainer-email: Psynosaur <psynosaur@gmail.com>
License: MIT
Project-URL: Homepage, https://github.com/Psynosaur/SemanticScout
Project-URL: Repository, https://github.com/Psynosaur/SemanticScout.git
Project-URL: Issues, https://github.com/Psynosaur/SemanticScout/issues
Project-URL: Documentation, https://github.com/Psynosaur/SemanticScout#readme
Keywords: mcp,context-engine,code-search,vector-database,ai-agents,semantic-search,ollama,chromadb
Classifier: Development Status :: 3 - Alpha
Classifier: Intended Audience :: Developers
Classifier: License :: OSI Approved :: MIT License
Classifier: Programming Language :: Python :: 3
Classifier: Programming Language :: Python :: 3.12
Classifier: Programming Language :: Python :: 3.13
Classifier: Topic :: Software Development :: Libraries :: Python Modules
Classifier: Topic :: Scientific/Engineering :: Artificial Intelligence
Requires-Python: >=3.12
License-File: LICENSE
Requires-Dist: mcp[cli]>=1.2.0
Requires-Dist: chromadb>=0.4.0
Requires-Dist: openai>=1.0.0
Requires-Dist: tree-sitter<0.22,>=0.20.0
Requires-Dist: tree-sitter-languages>=1.10.0
Requires-Dist: httpx>=0.25.0
Requires-Dist: pathspec>=0.11.0
Requires-Dist: watchdog>=3.0.0
Requires-Dist: python-dotenv>=1.0.0
Requires-Dist: networkx>=3.2.1
Requires-Dist: psutil>=5.9.0
Requires-Dist: sentence-transformers>=2.2.0
Provides-Extra: dev
Requires-Dist: pytest>=7.4.0; extra == "dev"
Requires-Dist: pytest-asyncio>=0.21.0; extra == "dev"
Requires-Dist: pytest-mock>=3.11.0; extra == "dev"
Requires-Dist: pytest-cov>=4.1.0; extra == "dev"
Requires-Dist: pytest-benchmark>=4.0.0; extra == "dev"
Requires-Dist: black>=23.0.0; extra == "dev"
Requires-Dist: ruff>=0.1.0; extra == "dev"
Requires-Dist: mypy>=1.5.0; extra == "dev"
Provides-Extra: fast
Requires-Dist: sentence-transformers>=2.2.0; extra == "fast"
Provides-Extra: gpu
Requires-Dist: torch>=2.0.0; extra == "gpu"
Requires-Dist: torchvision>=0.15.0; extra == "gpu"
Requires-Dist: torchaudio>=2.0.0; extra == "gpu"
Dynamic: license-file
